AthenaCSS/__init__.py
AthenaCSS/data/__init__.py
AthenaCSS/functions/__init__.py
AthenaCSS/models/__init__.py
AthenaCSS/models/athenalib_imports.py
AthenaCSS/models/generator.py
AthenaCSS-0.8.0.dist-info/LICENSE
AthenaCSS-0.8.0.dist-info/METADATA
AthenaCSS-0.8.0.dist-info/WHEEL
AthenaCSS-0.8.0.dist-info/top_level.txt
AthenaCSS-0.8.0.dist-info/RECORD
