Metadata-Version: 2.1
Name: AthenaCSS
Version: 0.8.0
Summary: CSS generator for Python
Home-page: https://github.com/DirectiveAthena/VerSC-AthenaCSS
Author: Andreas Sas
Author-email: 
License: GPLv3
Project-URL: Bug Tracker, https://github.com/DirectiveAthena/VerSC-AthenaCSS/issues
Requires-Python: >=3.10
License-File: LICENSE
Requires-Dist: AthenaColor (>=6.2.0)
Requires-Dist: AthenaLib (>=1.4.0)
